{
  "projectId": "proj_12345",
  "projectName": "Localisation de la page d'accueil Figma",
  "status": "ReadyForCompletion",
  "targetLanguages": [
    {
      "languageCode": "fr-FR",
      "status": "Importé"
    },
    {
      "languageCode": "De-DE",
      "status": "Annulé"
    },
    {
      "languageCode": "es-ES",
      "status": "Importé"
    }
  ],
  "canCompleteProject": true,
  "completionValidation": {
    "allLanguagesFinalized": true,
    "allowedStates": [
      "Importé",
      "Annulé"
    ]
  }
}